django_model_cached_property/__init__.py
django_model_cached_property/invalidate_model_cached_property.py
django_model_cached_property/model_cached_property.py
django_model_cached_property-0.0.2.dist-info/AUTHORS.md
django_model_cached_property-0.0.2.dist-info/AUTHORS.txt
django_model_cached_property-0.0.2.dist-info/LICENSE.md
django_model_cached_property-0.0.2.dist-info/METADATA
django_model_cached_property-0.0.2.dist-info/WHEEL
django_model_cached_property-0.0.2.dist-info/top_level.txt
django_model_cached_property-0.0.2.dist-info/RECORD
