Metadata-Version: 2.1
Name: django-model-cached-property
Version: 0.0.2
Summary: Django model cached property
Home-page: https://github.com/Legotckoi/django_model_cached_property/
Author: Evgenii Legotckoi
Author-email: legotskoy@gmail.com
License: MIT License
Project-URL: Bug Tracker, https://github.com/Legotckoi/django_model_cached_property/issues
Project-URL: repository, https://github.com/Legotckoi/django_model_cached_property
Keywords: django model cached property
Classifier: Development Status :: 5 - Production/Stable
Classifier: Environment :: Web Environment
Classifier: Framework :: Django
Classifier: Intended Audience :: Developers
Classifier: License :: OSI Approved :: MIT License
Classifier: Operating System :: OS Independent
Classifier: Programming Language :: Python
Classifier: Programming Language :: Python :: 3.5
Classifier: Programming Language :: Python :: 3.6
Classifier: Programming Language :: Python :: 3.7
Classifier: Programming Language :: Python :: 3.8
Classifier: Topic :: Internet :: WWW/HTTP
Classifier: Topic :: Internet :: WWW/HTTP :: Dynamic Content
Requires-Python: >=3.5
License-File: LICENSE.md
License-File: AUTHORS.md
License-File: AUTHORS.txt
Requires-Dist: Django
Requires-Dist: redis
Requires-Dist: django-redis
